sample_stainless/__init__.py
sample_stainless/_base_client.py
sample_stainless/_client.py
sample_stainless/_compat.py
sample_stainless/_constants.py
sample_stainless/_exceptions.py
sample_stainless/_files.py
sample_stainless/_models.py
sample_stainless/_qs.py
sample_stainless/_resource.py
sample_stainless/_response.py
sample_stainless/_streaming.py
sample_stainless/_types.py
sample_stainless/_version.py
sample_stainless/py.typed
sample_stainless/_utils/__init__.py
sample_stainless/_utils/_logs.py
sample_stainless/_utils/_proxy.py
sample_stainless/_utils/_reflection.py
sample_stainless/_utils/_streams.py
sample_stainless/_utils/_sync.py
sample_stainless/_utils/_transform.py
sample_stainless/_utils/_typing.py
sample_stainless/_utils/_utils.py
sample_stainless/lib/.keep
sample_stainless/resources/__init__.py
sample_stainless/resources/pets.py
sample_stainless/types/__init__.py
sample_stainless/types/new_pet.py
sample_stainless/types/pet.py
sample_stainless/types/pet_add_all_params.py
sample_stainless/types/pet_add_params.py
sample_stainless/types/pet_get_pets_params.py
sample_stainless/types/pet_list_params.py
sample_stainless/types/pet_list_response.py
sample_stainless_78-0.1.0a3.dist-info/METADATA
sample_stainless_78-0.1.0a3.dist-info/WHEEL
sample_stainless_78-0.1.0a3.dist-info/licenses/LICENSE
sample_stainless_78-0.1.0a3.dist-info/RECORD
